[
{"type":"oPID","name":"_Blank Node-N1","display":"_Blank Node","group":false,"depends":[]},
{"type":"property","name":"crm:P2.has type-N6","display":"crm:P2.has type","group":"crm","depends":["_Blank Node-N1"]},
{"type":"object","name":"crm:E16.Measurement","display":"crm:E16.Measurement","group":false,"depends":["crm:P2.has type-N6"]},
{"type":"property","name":"crm:P2.has type-N7","display":"crm:P2.has type","group":"crm","depends":["_Blank Node-N1"]},
{"type":"type","name":"aat:300081685","display":"aat:300081685","group":false,"depends":["crm:P2.has type-N7"]},
{"type":"property","name":"crm:P32.used general technique-N8","display":"crm:P32.used general technique","group":"crm","depends":["_Blank Node-N1"]},
{"type":"type","name":"aat:300223948","display":"aat:300223948","group":false,"depends":["crm:P32.used general technique-N8"]},
{"type":"property","name":"crm:P33.used specific technique-N9","display":"crm:P33.used specific technique","group":"crm","depends":["_Blank Node-N1"]},
{"type":"literal","name":"ngi:M0001","display":"ngi:M0001","group":false,"depends":["crm:P33.used specific technique-N9"]},
{"type":"property","name":"rdfs:comment-N10","display":"rdfs:comment","group":"rdfs","depends":["_Blank Node-N1"]},
{"type":"literal","name":"GC\u00adMS analysis of OS8 a grey\/white paint sample from the parapet behind the Virgin\u2019s throne@en","display":"GC\u00adMS analysis of OS8 a grey\/white paint sample from the\nparapet behind the Virgin\u2019s throne@en","group":false,"depends":["rdfs:comment-N10"]},
{"type":"property","name":"crm:P70.is documented in-N11","display":"crm:P70.is documented in","group":"crm","depends":["_Blank Node-N1"]},
{"type":"literal","name":"ngi:R000001","display":"ngi:R000001","group":false,"depends":["crm:P70.is documented in-N11"]},
{"type":"property","name":"crm:P108.has produced-N12","display":"crm:P108.has produced","group":"crm","depends":["_Blank Node-N1"]},
{"type":"literal","name":"ngi:NG1171\u00ad-OS8-\u00adGC","display":"ngi:NG1171\u00ad-OS8-\u00adGC","group":false,"depends":["crm:P108.has produced-N12","owl:sameAs-N28"]},
{"type":"property","name":"crm:P14.carried out by-N13","display":"crm:P14.carried out by","group":"crm","depends":["_Blank Node-N1"]},
{"type":"oPID","name":"ngo:00D-0002-0000","display":"ngo:00D-0002-0000","group":false,"depends":["crm:P14.carried out by-N13"]},
{"type":"property","name":"crm:P39.measured-N14","display":"crm:P39.measured","group":"crm","depends":["_Blank Node-N1"]},
{"type":"literal","name":"ngi:NG1171\u00ad-OS8","display":"ngi:NG1171\u00ad-OS8","group":false,"depends":["crm:P39.measured-N14","crm:P13.destroyed-N23"]},
{"type":"property","name":"crm:P2.has type-N16","display":"crm:P2.has type","group":"crm","depends":["ngi:NG1171\u00ad-OS8-\u00adGC"]},
{"type":"object","name":"crm:E73.Informational Object","display":"crm:E73.Informational Object","group":false,"depends":["crm:P2.has type-N16"]},
{"type":"property","name":"crm:P2.has type-N17","display":"crm:P2.has type","group":"crm","depends":["ngi:NG1171\u00ad-OS8-\u00adGC"]},
{"type":"type","name":"wd:Q1172284","display":"wd:Q1172284","group":false,"depends":["crm:P2.has type-N17"]},
{"type":"property","name":"rdfs:label-N18","display":"rdfs:label","group":"rdfs","depends":["wd:Q1172284"]},
{"type":"literal","name":"data set@en","display":"data set@en","group":false,"depends":["rdfs:label-N18"]},
{"type":"property","name":"crm:P2.has type-N19","display":"crm:P2.has type","group":"crm","depends":["ngi:NG1171\u00ad-OS8-\u00adGC"]},
{"type":"type","name":"wd:Q3192054","display":"wd:Q3192054","group":false,"depends":["crm:P2.has type-N19"]},
{"type":"property","name":"rdfs:label-N20","display":"rdfs:label","group":"rdfs","depends":["wd:Q3192054"]},
{"type":"literal","name":"chromatogram@en","display":"chromatogram@en","group":false,"depends":["rdfs:label-N20"]},
{"type":"oPID","name":"_Blank Node-N2","display":"_Blank Node","group":false,"depends":["owl:sameAs-N24"]},
{"type":"property","name":"crm:P2.has type-N22","display":"crm:P2.has type","group":"crm","depends":["_Blank Node-N2"]},
{"type":"object","name":"crm:E6.Destruction","display":"crm:E6.Destruction","group":false,"depends":["crm:P2.has type-N22"]},
{"type":"property","name":"crm:P13.destroyed-N23","display":"crm:P13.destroyed","group":"crm","depends":["_Blank Node-N2"]},
{"type":"property","name":"owl:sameAs-N24","display":"owl:sameAs","group":"owl","depends":["_Blank Node-N1"]},
{"type":"oPID","name":"_Blank Node-N3","display":"_Blank Node","group":false,"depends":["crm:P40.observed dimension-N27"]},
{"type":"property","name":"crm:P2.has type-N26","display":"crm:P2.has type","group":"crm","depends":["_Blank Node-N3"]},
{"type":"object","name":"crm:E54.Dimension","display":"crm:E54.Dimension","group":false,"depends":["crm:P2.has type-N26","crm:P2.has type-N30","crm:P2.has type-N41","crm:P2.has type-N52"]},
{"type":"property","name":"crm:P40.observed dimension-N27","display":"crm:P40.observed dimension","group":"crm","depends":["_Blank Node-N1"]},
{"type":"property","name":"owl:sameAs-N28","display":"owl:sameAs","group":"owl","depends":["_Blank Node-N3"]},
{"type":"oPID","name":"_Blank Node-N4","display":"_Blank Node","group":false,"depends":["crm:P43.has dimension-N32","crm:P141.assigned-N38"]},
{"type":"property","name":"crm:P2.has type-N30","display":"crm:P2.has type","group":"crm","depends":["_Blank Node-N4"]},
{"type":"property","name":"crm:P2.has type-N31","display":"crm:P2.has type","group":"crm","depends":["_Blank Node-N4"]},
{"type":"oPID","name":"ngo:00A\u00ad-00E5-0000","display":"ngo:00A\u00ad-00E5-0000","group":false,"depends":["crm:P2.has type-N31"]},
{"type":"property","name":"crm:P43.has dimension-N32","display":"crm:P43.has dimension","group":"crm","depends":["ngi:NG1171\u00ad-OS8-\u00adGC"]},
{"type":"property","name":"crm:P90.has value-N33","display":"crm:P90.has value","group":"crm","depends":["_Blank Node-N4"]},
{"type":"literal","name":"2.9#xsd:float","display":"2.9#xsd:float","group":false,"depends":["crm:P90.has value-N33"]},
{"type":"property","name":"rdfs:label-N34","display":"rdfs:label","group":"rdfs","depends":["ngo:00A\u00ad-00E5-0000"]},
{"type":"literal","name":"palmitate to stearate ratio@en","display":"palmitate to stearate ratio@en","group":false,"depends":["rdfs:label-N34"]},
{"type":"oPID","name":"_Blank Node-N5","display":"_Blank Node","group":false,"depends":[]},
{"type":"property","name":"crm:P2.has type-N36","display":"crm:P2.has type","group":"crm","depends":["_Blank Node-N5"]},
{"type":"object","name":"crm:E13.Attribution Assignment","display":"crm:E13.Attribution Assignment","group":false,"depends":["crm:P2.has type-N36","crm:P2.has type-N47","crm:P2.has type-N58","crm:P2.has type-N77"]},
{"type":"property","name":"crm:P140.assigned attribute to-N37","display":"crm:P140.assigned attribute to","group":"crm","depends":["_Blank Node-N5"]},
{"type":"literal","name":"ngi:NG1171-OS8-MS","display":"ngi:NG1171-OS8-MS","group":false,"depends":["crm:P140.assigned attribute to-N37","crm:P16.used specific object-N39","crm:P140.assigned attribute to-N48","crm:P16.used specific object-N50","crm:P140.assigned attribute to-N59","crm:P16.used specific object-N61","crm:P16.used specific object-N79"]},
{"type":"property","name":"crm:P141.assigned-N38","display":"crm:P141.assigned","group":"crm","depends":["_Blank Node-N5"]},
{"type":"property","name":"crm:P16.used specific object-N39","display":"crm:P16.used specific object","group":"crm","depends":["_Blank Node-N5"]},
{"type":"oPID","name":"_Blank Node-N6","display":"_Blank Node","group":false,"depends":["crm:P43.has dimension-N43","crm:P141.assigned-N49"]},
{"type":"property","name":"crm:P2.has type-N41","display":"crm:P2.has type","group":"crm","depends":["_Blank Node-N6"]},
{"type":"property","name":"crm:P2.has type-N42","display":"crm:P2.has type","group":"crm","depends":["_Blank Node-N6"]},
{"type":"oPID","name":"ngo:00A-\u00ad00E6-\u00ad0000","display":"ngo:00A-\u00ad00E6-\u00ad0000","group":false,"depends":["crm:P2.has type-N42"]},
{"type":"property","name":"crm:P43.has dimension-N43","display":"crm:P43.has dimension","group":"crm","depends":["ngi:NG1171\u00ad-OS8-\u00adGC"]},
{"type":"property","name":"crm:P90.has value-N44","display":"crm:P90.has value","group":"crm","depends":["_Blank Node-N6"]},
{"type":"literal","name":"2.2#xsd:float","display":"2.2#xsd:float","group":false,"depends":["crm:P90.has value-N44"]},
{"type":"property","name":"rdfs:label-N45","display":"rdfs:label","group":"rdfs","depends":["ngo:00A-\u00ad00E6-\u00ad0000"]},
{"type":"literal","name":"azelate to palmitate ratio@en","display":"azelate to palmitate ratio@en","group":false,"depends":["rdfs:label-N45"]},
{"type":"oPID","name":"_Blank Node-N7","display":"_Blank Node","group":false,"depends":[]},
{"type":"property","name":"crm:P2.has type-N47","display":"crm:P2.has type","group":"crm","depends":["_Blank Node-N7"]},
{"type":"property","name":"crm:P140.assigned attribute to-N48","display":"crm:P140.assigned attribute to","group":"crm","depends":["_Blank Node-N7"]},
{"type":"property","name":"crm:P141.assigned-N49","display":"crm:P141.assigned","group":"crm","depends":["_Blank Node-N7"]},
{"type":"property","name":"crm:P16.used specific object-N50","display":"crm:P16.used specific object","group":"crm","depends":["_Blank Node-N7"]},
{"type":"oPID","name":"_Blank Node-N8","display":"_Blank Node","group":false,"depends":["crm:P43.has dimension-N54","crm:P141.assigned-N60"]},
{"type":"property","name":"crm:P2.has type-N52","display":"crm:P2.has type","group":"crm","depends":["_Blank Node-N8"]},
{"type":"property","name":"crm:P2.has type-N53","display":"crm:P2.has type","group":"crm","depends":["_Blank Node-N8"]},
{"type":"oPID","name":"ngo:00A-\u00ad00E7-\u00ad0000","display":"ngo:00A-\u00ad00E7-\u00ad0000","group":false,"depends":["crm:P2.has type-N53"]},
{"type":"property","name":"crm:P43.has dimension-N54","display":"crm:P43.has dimension","group":"crm","depends":["ngi:NG1171\u00ad-OS8-\u00adGC"]},
{"type":"property","name":"crm:P90.has value-N55","display":"crm:P90.has value","group":"crm","depends":["_Blank Node-N8"]},
{"type":"literal","name":"2.7#xsd:float","display":"2.7#xsd:float","group":false,"depends":["crm:P90.has value-N55"]},
{"type":"property","name":"rdfs:label-N56","display":"rdfs:label","group":"rdfs","depends":["ngo:00A-\u00ad00E7-\u00ad0000"]},
{"type":"literal","name":"azelate to suberate ratio@en","display":"azelate to suberate ratio@en","group":false,"depends":["rdfs:label-N56"]},
{"type":"oPID","name":"_Blank Node-N9","display":"_Blank Node","group":false,"depends":[]},
{"type":"property","name":"crm:P2.has type-N58","display":"crm:P2.has type","group":"crm","depends":["_Blank Node-N9"]},
{"type":"property","name":"crm:P140.assigned attribute to-N59","display":"crm:P140.assigned attribute to","group":"crm","depends":["_Blank Node-N9"]},
{"type":"property","name":"crm:P141.assigned-N60","display":"crm:P141.assigned","group":"crm","depends":["_Blank Node-N9"]},
{"type":"property","name":"crm:P16.used specific object-N61","display":"crm:P16.used specific object","group":"crm","depends":["_Blank Node-N9"]},
{"type":"property","name":"crm:P2.has type-N63","display":"crm:P2.has type","group":"crm","depends":["ngo:00D-0002-0000"]},
{"type":"object","name":"crm:E21.Person","display":"crm:E21.Person","group":false,"depends":["crm:P2.has type-N63"]},
{"type":"property","name":"crm:P2.has type-N64","display":"crm:P2.has type","group":"crm","depends":["ngo:00D-0002-0000"]},
{"type":"type","name":"aat:300025820","display":"aat:300025820","group":false,"depends":["crm:P2.has type-N64"]},
{"type":"property","name":"rdfs:label-N65","display":"rdfs:label","group":"rdfs","depends":["ngo:00D-0002-0000"]},
{"type":"literal","name":"Example NG Staff Member@en","display":"Example NG Staff Member@en","group":false,"depends":["rdfs:label-N65"]},
{"type":"property","name":"rdfs:label-N67","display":"rdfs:label","group":"rdfs","depends":["aat:300025820"]},
{"type":"literal","name":"conservation scientist@en","display":"conservation scientist@en","group":false,"depends":["rdfs:label-N67"]},
{"type":"property","name":"crm:P2.has type-N69","display":"crm:P2.has type","group":"crm","depends":["ngi:R000001"]},
{"type":"object","name":"crm:E31.Document","display":"crm:E31.Document","group":false,"depends":["crm:P2.has type-N69"]},
{"type":"property","name":"rdfs:label-N70","display":"rdfs:label","group":"rdfs","depends":["ngi:R000001"]},
{"type":"literal","name":"Organic Report for NG1171@en","display":"Organic Report for NG1171@en","group":false,"depends":["rdfs:label-N70"]},
{"type":"property","name":"rdfs:label-N72","display":"rdfs:label","group":"rdfs","depends":["ngi:M0001"]},
{"type":"literal","name":"NG GC-MS Method 2009@en","display":"NG GC-MS Method 2009@en","group":false,"depends":["rdfs:label-N72"]},
{"type":"property","name":"crm:P2.has type-N73","display":"crm:P2.has type","group":"crm","depends":["ngi:M0001"]},
{"type":"object","name":"crm:E29.Design or Procedure","display":"crm:E29.Design or Procedure","group":false,"depends":["crm:P2.has type-N73"]},
{"type":"property","name":"rdfs:label-N74","display":"rdfs:label","group":"rdfs","depends":["aat:300081685"]},
{"type":"literal","name":"chemical analysis@en","display":"chemical analysis@en","group":false,"depends":["rdfs:label-N74"]},
{"type":"property","name":"rdfs:label-N75","display":"rdfs:label","group":"rdfs","depends":["aat:300223948"]},
{"type":"literal","name":"gas chromatography@en","display":"gas chromatography@en","group":false,"depends":["rdfs:label-N75"]},
{"type":"oPID","name":"_Blank Node-N10","display":"_Blank Node","group":false,"depends":[]},
{"type":"property","name":"crm:P2.has type-N77","display":"crm:P2.has type","group":"crm","depends":["_Blank Node-N10"]},
{"type":"property","name":"crm:P140.assigned attribute to-N78","display":"crm:P140.assigned attribute to","group":"crm","depends":["_Blank Node-N10"]},
{"type":"literal","name":"ngi:NG1171-OS8","display":"ngi:NG1171-OS8","group":false,"depends":["crm:P140.assigned attribute to-N78"]},
{"type":"property","name":"crm:P16.used specific object-N79","display":"crm:P16.used specific object","group":"crm","depends":["_Blank Node-N10"]},
{"type":"oPID","name":"_Blank Node-N11","display":"_Blank Node","group":false,"depends":["crm:P141.assigned-N84","crm:P46.is composed of-N85"]},
{"type":"property","name":"crm:P2.has type-N81","display":"crm:P2.has type","group":"crm","depends":["_Blank Node-N11"]},
{"type":"object","name":"crm:E57.Material","display":"crm:E57.Material","group":false,"depends":["crm:P2.has type-N81"]},
{"type":"property","name":"crm:P2.has type-N82","display":"crm:P2.has type","group":"crm","depends":["_Blank Node-N11"]},
{"type":"type","name":"aat:300163343","display":"aat:300163343","group":false,"depends":["crm:P2.has type-N82"]},
{"type":"property","name":"crm:P45.consists of-N83","display":"crm:P45.consists of","group":"crm","depends":["_Blank Node-N11"]},
{"type":"type","name":"aat:300014310","display":"aat:300014310","group":false,"depends":["crm:P45.consists of-N83"]},
{"type":"property","name":"crm:P141.assigned-N84","display":"crm:P141.assigned","group":"crm","depends":["_Blank Node-N10"]},
{"type":"property","name":"crm:P46.is composed of-N85","display":"crm:P46.is composed of","group":"crm","depends":["ngi:NG1171-OS8"]},
{"type":"property","name":"rdfs:label-N87","display":"rdfs:label","group":"rdfs","depends":["aat:300014310"]},
{"type":"literal","name":"walnut oil@en","display":"walnut oil@en","group":false,"depends":["rdfs:label-N87"]},
{"type":"property","name":"rdfs:label-N88","display":"rdfs:label","group":"rdfs","depends":["aat:300163343"]},
{"type":"literal","name":"media (artists' materials)@en","display":"media (artists' materials)@en","group":false,"depends":["rdfs:label-N88"]}]